chanmqttproxy/__init__.py
chanmqttproxy/channelsmqttproxy.py
chanmqttproxy/mqttconsumer.py
chanmqttproxy-0.1.dist-info/LICENSE
chanmqttproxy-0.1.dist-info/METADATA
chanmqttproxy-0.1.dist-info/WHEEL
chanmqttproxy-0.1.dist-info/top_level.txt
chanmqttproxy-0.1.dist-info/RECORD
