Metadata-Version: 2.1
Name: chanmqttproxy
Version: 0.1
Summary: Channels Worker providing async (qmqtt) MQTT proxy
Home-page: https://github.com/lbt/channels-mqtt-proxy
Author: David Greaves
Author-email: david@dgreaves.com
License: GPLv3+
Platform: UNKNOWN
Classifier: Development Status :: 4 - Beta
Classifier: Environment :: Web Environment
Classifier: License :: OSI Approved :: GNU General Public License v3 or later (GPLv3+)
Classifier: Framework :: Django
Classifier: Operating System :: OS Independent
Classifier: Programming Language :: Python
Classifier: Programming Language :: Python :: 3
Classifier: Programming Language :: Python :: 3.7
License-File: LICENSE
Requires-Dist: gmqtt
